szitas_logger/__init__.py
szitas_logger/logger.py
szitas_logger-1.0.0.dist-info/AUTHORS
szitas_logger-1.0.0.dist-info/LICENSE.md
szitas_logger-1.0.0.dist-info/METADATA
szitas_logger-1.0.0.dist-info/WHEEL
szitas_logger-1.0.0.dist-info/top_level.txt
szitas_logger-1.0.0.dist-info/RECORD
