Metadata-Version: 2.1
Name: szitas-logger
Version: 1.0.0
Summary: This project is my japl (just another python logger) project which I'm using
Home-page: https://szitasg.github.io/
Author: Gábor Szitás
Author-email: gabor.szitas.work@gmail.com
Project-URL: Source Code, https://github.com/szitasg/szitas-logger
Classifier: Development Status :: 5 - Production/Stable
Classifier: Intended Audience :: Developers
Classifier: Intended Audience :: Information Technology
Classifier: License :: OSI Approved :: Apache Software License
Classifier: Operating System :: OS Independent
Classifier: Programming Language :: Python
Classifier: Programming Language :: Python :: 3
Classifier: Programming Language :: Python :: 3.6
Classifier: Programming Language :: Python :: 3.10
Requires-Python: >=3.6
License-File: LICENSE.md
